claude_model_selector/__init__.py
claude_model_selector/cli.py
claude_model_selector/config.json
claude_model_selector/selector.py
claude_model_selector-1.0.0.dist-info/licenses/LICENSE
claude_model_selector-1.0.0.dist-info/METADATA
claude_model_selector-1.0.0.dist-info/WHEEL
claude_model_selector-1.0.0.dist-info/entry_points.txt
claude_model_selector-1.0.0.dist-info/top_level.txt
claude_model_selector-1.0.0.dist-info/RECORD
