Metadata-Version: 2.4
Name: claude-model-selector
Version: 1.0.0
Summary: Intelligent model selection for optimal cost-effectiveness with Anthropic's Claude AI
Home-page: https://github.com/aeonbridge/claude-model-selector
Author: AeonBridge Co.
Author-email: "AeonBridge Co." <support@aeonbridge.com>
Maintainer-email: "AeonBridge Co." <support@aeonbridge.com>
License: MIT
Project-URL: Homepage, https://github.com/aeonbridge/claude-model-selector
Project-URL: Documentation, https://github.com/aeonbridge/claude-model-selector#readme
Project-URL: Repository, https://github.com/aeonbridge/claude-model-selector
Project-URL: Bug Tracker, https://github.com/aeonbridge/claude-model-selector/issues
Project-URL: Discussions, https://github.com/aeonbridge/claude-model-selector/discussions
Project-URL: Changelog, https://github.com/aeonbridge/claude-model-selector/blob/main/CHANGELOG.md
Keywords: claude,anthropic,ai,model-selection,cost-optimization,llm,gpt,machine-learning,artificial-intelligence
Classifier: Development Status :: 5 - Production/Stable
Classifier: Intended Audience :: Developers
Classifier: Topic :: Software Development :: Libraries :: Python Modules
Classifier: Topic :: Scientific/Engineering :: Artificial Intelligence
Classifier: Programming Language :: Python :: 3
Classifier: Programming Language :: Python :: 3.8
Classifier: Programming Language :: Python :: 3.9
Classifier: Programming Language :: Python :: 3.10
Classifier: Programming Language :: Python :: 3.11
Classifier: Programming Language :: Python :: 3.12
Classifier: Operating System :: OS Independent
Classifier: Natural Language :: English
Requires-Python: >=3.8
License-File: LICENSE
Provides-Extra: dev
Requires-Dist: pytest>=7.0.0; extra == "dev"
Requires-Dist: pytest-cov>=4.0.0; extra == "dev"
Requires-Dist: black>=23.0.0; extra == "dev"
Requires-Dist: flake8>=6.0.0; extra == "dev"
Requires-Dist: mypy>=1.0.0; extra == "dev"
Requires-Dist: build>=0.10.0; extra == "dev"
Requires-Dist: twine>=4.0.0; extra == "dev"
Dynamic: author
Dynamic: home-page
Dynamic: license-file
Dynamic: requires-python
